hitchenvironment
